bugsnag/__init__.py
bugsnag/asgi.py
bugsnag/breadcrumbs.py
bugsnag/client.py
bugsnag/configuration.py
bugsnag/context.py
bugsnag/delivery.py
bugsnag/error.py
bugsnag/event.py
bugsnag/feature_flags.py
bugsnag/handlers.py
bugsnag/legacy.py
bugsnag/middleware.py
bugsnag/notification.py
bugsnag/notifier.py
bugsnag/py.typed
bugsnag/request_tracker.py
bugsnag/sessiontracker.py
bugsnag/utils.py
bugsnag/uwsgi.py
bugsnag/celery/__init__.py
bugsnag/django/__init__.py
bugsnag/django/middleware.py
bugsnag/django/utils.py
bugsnag/flask/__init__.py
bugsnag/tornado/__init__.py
bugsnag/wsgi/__init__.py
bugsnag/wsgi/middleware.py
bugsnag-4.8.1.dist-info/licenses/LICENSE.txt
bugsnag-4.8.1.dist-info/METADATA
bugsnag-4.8.1.dist-info/WHEEL
bugsnag-4.8.1.dist-info/top_level.txt
bugsnag-4.8.1.dist-info/RECORD
